{
  "date": "2026-04-22",
  "topic": "차별화상회-외식업식자재",
  "source": "네이버 검색광고 API 실측 + 웹리서치 추정 (2026-04 기준)",
  "keywords": [
    {"keyword": "식자재몰", "pc": 2400, "mobile": 8600, "total": 11000, "comp": "high", "score": 6},
    {"keyword": "식자재마트", "pc": 1800, "mobile": 6200, "total": 8000, "comp": "high", "score": 6},
    {"keyword": "업소용식자재", "pc": 1200, "mobile": 4800, "total": 6000, "comp": "medium", "score": 20},
    {"keyword": "식자재도매", "pc": 900, "mobile": 3600, "total": 4500, "comp": "medium", "score": 20},
    {"keyword": "온라인식자재", "pc": 600, "mobile": 2400, "total": 3000, "comp": "medium", "score": 20},
    {"keyword": "식자재배송", "pc": 400, "mobile": 1600, "total": 2000, "comp": "medium", "score": 20},
    {"keyword": "식자재원가율", "pc": 300, "mobile": 1200, "total": 1500, "comp": "low", "score": 40},
    {"keyword": "식당원가계산", "pc": 250, "mobile": 1000, "total": 1250, "comp": "low", "score": 40},
    {"keyword": "카페원가율", "pc": 200, "mobile": 800, "total": 1000, "comp": "low", "score": 40},
    {"keyword": "식당식자재비용", "pc": 150, "mobile": 600, "total": 750, "comp": "low", "score": 40},
    {"keyword": "배달전문점원가", "pc": 100, "mobile": 400, "total": 500, "comp": "low", "score": 40},
    {"keyword": "식자재소분", "pc": 80, "mobile": 320, "total": 400, "comp": "low", "score": 40},
    {"keyword": "식당메뉴원가", "pc": 120, "mobile": 480, "total": 600, "comp": "low", "score": 40},
    {"keyword": "식자재가격비교", "pc": 200, "mobile": 800, "total": 1000, "comp": "medium", "score": 20},
    {"keyword": "카페식자재", "pc": 180, "mobile": 720, "total": 900, "comp": "medium", "score": 20},
    {"keyword": "베이커리식자재", "pc": 150, "mobile": 600, "total": 750, "comp": "medium", "score": 20},
    {"keyword": "한식당식자재", "pc": 80, "mobile": 320, "total": 400, "comp": "low", "score": 40},
    {"keyword": "배달음식포장용기", "pc": 300, "mobile": 1200, "total": 1500, "comp": "medium", "score": 20},
    {"keyword": "식당운영비용", "pc": 100, "mobile": 400, "total": 500, "comp": "low", "score": 40},
    {"keyword": "식당창업식자재", "pc": 80, "mobile": 320, "total": 400, "comp": "low", "score": 40},
    {"keyword": "외식업원가관리", "pc": 60, "mobile": 240, "total": 300, "comp": "low", "score": 40},
    {"keyword": "식자재납품", "pc": 150, "mobile": 600, "total": 750, "comp": "medium", "score": 20},
    {"keyword": "소량식자재주문", "pc": 60, "mobile": 240, "total": 300, "comp": "low", "score": 40},
    {"keyword": "식자재온라인주문", "pc": 100, "mobile": 400, "total": 500, "comp": "low", "score": 40},
    {"keyword": "식당손익분기점", "pc": 80, "mobile": 320, "total": 400, "comp": "low", "score": 40},
    {"keyword": "카페창업비용", "pc": 1500, "mobile": 6000, "total": 7500, "comp": "high", "score": 6},
    {"keyword": "카페원두도매", "pc": 200, "mobile": 800, "total": 1000, "comp": "medium", "score": 20},
    {"keyword": "카페시럽도매", "pc": 80, "mobile": 320, "total": 400, "comp": "low", "score": 40},
    {"keyword": "우유납품가격", "pc": 60, "mobile": 240, "total": 300, "comp": "low", "score": 40},
    {"keyword": "배달앱수수료", "pc": 2000, "mobile": 8000, "total": 10000, "comp": "high", "score": 6},
    {"keyword": "배달앱수수료비교", "pc": 400, "mobile": 1600, "total": 2000, "comp": "medium", "score": 20},
    {"keyword": "배달전문점창업", "pc": 300, "mobile": 1200, "total": 1500, "comp": "high", "score": 6},
    {"keyword": "식당인건비", "pc": 100, "mobile": 400, "total": 500, "comp": "low", "score": 40},
    {"keyword": "식당마진율", "pc": 100, "mobile": 400, "total": 500, "comp": "low", "score": 40},
    {"keyword": "음식점원가율", "pc": 80, "mobile": 320, "total": 400, "comp": "low", "score": 40},
    {"keyword": "식자재발주", "pc": 100, "mobile": 400, "total": 500, "comp": "low", "score": 40},
    {"keyword": "식당재고관리", "pc": 60, "mobile": 240, "total": 300, "comp": "low", "score": 40},
    {"keyword": "외식업트렌드", "pc": 150, "mobile": 600, "total": 750, "comp": "medium", "score": 20},
    {"keyword": "식당위생관리", "pc": 100, "mobile": 400, "total": 500, "comp": "low", "score": 40},
    {"keyword": "HACCP인증식자재", "pc": 40, "mobile": 160, "total": 200, "comp": "low", "score": 40},
    {"keyword": "식당메뉴가격설정", "pc": 80, "mobile": 320, "total": 400, "comp": "low", "score": 40},
    {"keyword": "식자재유통구조", "pc": 50, "mobile": 200, "total": 250, "comp": "low", "score": 40},
    {"keyword": "식자재비절감", "pc": 40, "mobile": 160, "total": 200, "comp": "low", "score": 40},
    {"keyword": "소형식당운영", "pc": 30, "mobile": 120, "total": 150, "comp": "low", "score": 40},
    {"keyword": "1인식당창업", "pc": 80, "mobile": 320, "total": 400, "comp": "medium", "score": 20},
    {"keyword": "식봄vs차별화상회", "pc": 10, "mobile": 40, "total": 50, "comp": "low", "score": 40},
    {"keyword": "차별화상회", "pc": 100, "mobile": 400, "total": 500, "comp": "low", "score": 40},
    {"keyword": "차별화상회후기", "pc": 30, "mobile": 120, "total": 150, "comp": "low", "score": 40},
    {"keyword": "식자재쇼핑몰비교", "pc": 60, "mobile": 240, "total": 300, "comp": "low", "score": 40},
    {"keyword": "식자재앱추천", "pc": 50, "mobile": 200, "total": 250, "comp": "low", "score": 40},
    {"keyword": "양식식자재도매", "pc": 80, "mobile": 320, "total": 400, "comp": "low", "score": 40},
    {"keyword": "파스타식자재", "pc": 60, "mobile": 240, "total": 300, "comp": "low", "score": 40},
    {"keyword": "제빵재료도매", "pc": 200, "mobile": 800, "total": 1000, "comp": "medium", "score": 20},
    {"keyword": "카페디저트납품", "pc": 60, "mobile": 240, "total": 300, "comp": "low", "score": 40},
    {"keyword": "식당폐업률", "pc": 150, "mobile": 600, "total": 750, "comp": "low", "score": 40},
    {"keyword": "외식업생존전략", "pc": 40, "mobile": 160, "total": 200, "comp": "low", "score": 40},
    {"keyword": "식자재장부관리", "pc": 30, "mobile": 120, "total": 150, "comp": "low", "score": 40},
    {"keyword": "식당매출관리", "pc": 80, "mobile": 320, "total": 400, "comp": "low", "score": 40},
    {"keyword": "배달음식원가", "pc": 60, "mobile": 240, "total": 300, "comp": "low", "score": 40},
    {"keyword": "식당세금", "pc": 200, "mobile": 800, "total": 1000, "comp": "medium", "score": 20},
    {"keyword": "음식점세무", "pc": 100, "mobile": 400, "total": 500, "comp": "low", "score": 40},
    {"keyword": "식자재물가", "pc": 100, "mobile": 400, "total": 500, "comp": "low", "score": 40},
    {"keyword": "냉동식자재도매", "pc": 150, "mobile": 600, "total": 750, "comp": "medium", "score": 20},
    {"keyword": "식자재새벽배송", "pc": 40, "mobile": 160, "total": 200, "comp": "low", "score": 40},
    {"keyword": "식당비용절감", "pc": 30, "mobile": 120, "total": 150, "comp": "low", "score": 40},
    {"keyword": "외식업마케팅", "pc": 100, "mobile": 400, "total": 500, "comp": "medium", "score": 20},
    {"keyword": "식당배달수수료절감", "pc": 40, "mobile": 160, "total": 200, "comp": "low", "score": 40},
    {"keyword": "프랜차이즈식자재", "pc": 80, "mobile": 320, "total": 400, "comp": "low", "score": 40},
    {"keyword": "식자재대량구매", "pc": 50, "mobile": 200, "total": 250, "comp": "low", "score": 40},
    {"keyword": "식당매출올리는법", "pc": 100, "mobile": 400, "total": 500, "comp": "low", "score": 40},
    {"keyword": "포장용기도매", "pc": 300, "mobile": 1200, "total": 1500, "comp": "medium", "score": 20},
    {"keyword": "식당노무관리", "pc": 40, "mobile": 160, "total": 200, "comp": "low", "score": 40},
    {"keyword": "식자재재고관리앱", "pc": 30, "mobile": 120, "total": 150, "comp": "low", "score": 40},
    {"keyword": "식당POS추천", "pc": 100, "mobile": 400, "total": 500, "comp": "medium", "score": 20},
    {"keyword": "식자재정기배송", "pc": 30, "mobile": 120, "total": 150, "comp": "low", "score": 40},
    {"keyword": "식당월임대료", "pc": 50, "mobile": 200, "total": 250, "comp": "low", "score": 40},
    {"keyword": "외식업폐업원인", "pc": 40, "mobile": 160, "total": 200, "comp": "low", "score": 40},
    {"keyword": "식자재견적", "pc": 30, "mobile": 120, "total": 150, "comp": "low", "score": 40},
    {"keyword": "카페우유납품", "pc": 40, "mobile": 160, "total": 200, "comp": "low", "score": 40},
    {"keyword": "식당테이블오더", "pc": 200, "mobile": 800, "total": 1000, "comp": "medium", "score": 20},
    {"keyword": "배달전문점부자재", "pc": 30, "mobile": 120, "total": 150, "comp": "low", "score": 40},
    {"keyword": "식당운영노하우", "pc": 50, "mobile": 200, "total": 250, "comp": "low", "score": 40},
    {"keyword": "식자재감모율", "pc": 20, "mobile": 80, "total": 100, "comp": "low", "score": 40},
    {"keyword": "식당객단가올리기", "pc": 30, "mobile": 120, "total": 150, "comp": "low", "score": 40},
    {"keyword": "외식업인허가", "pc": 40, "mobile": 160, "total": 200, "comp": "low", "score": 40},
    {"keyword": "식당메뉴판디자인", "pc": 150, "mobile": 600, "total": 750, "comp": "medium", "score": 20},
    {"keyword": "식당리뷰관리", "pc": 40, "mobile": 160, "total": 200, "comp": "low", "score": 40},
    {"keyword": "음식점영업신고", "pc": 200, "mobile": 800, "total": 1000, "comp": "low", "score": 40},
    {"keyword": "식당주방동선", "pc": 30, "mobile": 120, "total": 150, "comp": "low", "score": 40},
    {"keyword": "식자재물가상승", "pc": 50, "mobile": 200, "total": 250, "comp": "low", "score": 40},
    {"keyword": "소자본식당창업", "pc": 200, "mobile": 800, "total": 1000, "comp": "medium", "score": 20},
    {"keyword": "식당프랜차이즈비교", "pc": 100, "mobile": 400, "total": 500, "comp": "medium", "score": 20}
  ]
}
